MANIFEST.in
setup.py
bin/moncov
etc/moncov.yaml
lib/systemd/system/moncov.service
moncov/__init__.py
moncov/collector.py
moncov/conf.py
moncov/ctl.py
moncov/data.py
moncov/monkey.py
moncov/tracer.py
moncov.egg-info/PKG-INFO
moncov.egg-info/SOURCES.txt
moncov.egg-info/dependency_links.txt
moncov.egg-info/requires.txt
moncov.egg-info/top_level.txt
moncov/stats/__init__.py
moncov/stats/cobertura.py
moncov/stats/rate.py
moncov/stats/simple.py
test/test_branch_rate.py
test/test_line_rate.py
test/test_xml.py