Metadata-Version: 1.1
Name: moncov
Version: 0.5.16
Summary: Python remote code coverage using Redis
Home-page: https://github.com/RedHatQE/python-moncov
Author: Vitaly Kuznetsov
Author-email: vitty@redhat.com
License: GPLv3+
Platform: UNKNOWN
Classifier: License :: OSI Approved :: GNU General Public License v3 or later (GPLv3+)
Classifier: Programming Language :: Python
Classifier: Topic :: Software Development :: Libraries :: Python Modules
Classifier: Operating System :: POSIX
Classifier: Intended Audience :: Developers
Classifier: Development Status :: 4 - Beta
Provides: moncov
